tog/__init__.py
tog/cli.py
tog/db.py
tog/types.py
tog-0.3.0.dist-info/entry_points.txt
tog-0.3.0.dist-info/WHEEL
tog-0.3.0.dist-info/METADATA
tog-0.3.0.dist-info/RECORD
