Metadata-Version: 2.1
Name: tog
Version: 0.3.0
Summary: Command line tool for interacting with tog data server
License: MIT
Requires-Python: >=3.6,<4.0
Classifier: License :: OSI Approved :: MIT License
Classifier: Programming Language :: Python :: 3
Classifier: Programming Language :: Python :: 3.6
Classifier: Programming Language :: Python :: 3.7
Classifier: Programming Language :: Python :: 3.8
Classifier: Programming Language :: Python :: 3.9
Requires-Dist: attrs (>=19.3.0,<20.0.0)
Requires-Dist: docopt (>=0.6.2,<0.7.0)
Requires-Dist: psycopg2-binary (>=2.8.5,<3.0.0)
Requires-Dist: pydash (>=4.7.6,<5.0.0)
Requires-Dist: python-dateutil (>=2.8.1,<3.0.0)
Requires-Dist: pytz (>=2020.1,<2021.0)
Requires-Dist: tqdm (>=4.46.0,<5.0.0)
